setup.py
mysqlctl/__init__.py
mysqlctl/mysqlctl.py
mysqlctl.egg-info/PKG-INFO
mysqlctl.egg-info/SOURCES.txt
mysqlctl.egg-info/dependency_links.txt
mysqlctl.egg-info/requires.txt
mysqlctl.egg-info/top_level.txt
validpar/__init__.py
validpar/validpar.py